<?xml version="1.0" encoding="UTF-8"?>
<krpano version="1.17"
        onstart="startup"
        logkey="false"
        bgcolor="#ffffff"
        projectfloorplanurl=""
        projecttitleid="project_title"
        projectdescriptionid="">

  <!-- generated by Panotour Pro V2.0.0 64bits : 08-11-2018 16-32-28 -->
  <!-- Plugins and Spot Styles -->
  <include url="%FIRSTXML%/teste 1_skin.xml"/>
  <!-- Core actions -->
  <include url="%FIRSTXML%/teste 1_core.xml"/>
  <!-- Tour Messages -->
  <include url="%FIRSTXML%/teste 1_messages_en.xml"/>

  <action name="startup">
    if (s !== null, if (startscene === null, set(startscene, get(s));); );
    if (startscene === null,
      set(startscene, pano22);
    );
    mainloadscene(get(startscene));
    if (h !== null,
      if (v !== null,
        if (f !== null,
          lookat(get(h), get(v), get(f));
         ,
          lookat(get(h), get(v));
        );
      );
    );
  </action>

  <!-- 1 Groups -->

  <!-- Group Group 23 : 1 panoramas -->
  

<!-- **** @PanoName="teste 1" @PanoFile="/Users/home/Desktop/PANORAMAS/1/cubos/[Grupo 0]-IMG_2864_IMG_2868-5 imagens_0.jpg" **** -->
<scene name="pano22"
       heading="0"
       thumburl="%FIRSTXML%/teste_1_22/thumbnail.jpg"
       backgroundsound=""
       backgroundsoundloops="0"
       titleid="pano22_title"
       descriptionid=""
       multires="true"
       planar="false"
       full360="true">

    <autorotate horizon="4.050000" tofov="90.000000" waittime="1" speed="5"/>

    <panoview h="-10.800000" v="4.050000" fov="90.000000" hmin="-180" hmax="180" vmin="-90" vmax="90" fovmax="90" />
    <view fisheye="0"
          limitview="range"
          hlookatmin="-180"
          hlookatmax="180"
          vlookatmin="-90"
          vlookatmax="90"
          maxpixelzoom="1.0"
          fovmax="90"
          fov="90.000000"
          hlookat="-10.800000"
          vlookat="4.050000"/>

    <preview url="%FIRSTXML%/teste_1_22/preview.jpg" type="CUBESTRIP" striporder="FRBLUD"/>

    <image type="CUBE" multires="true" baseindex="0" tilesize="512">
      <level tiledimagewidth="2464" tiledimageheight="2464">
        <front url="teste_1_22/0/2/%v_%u.jpg"/>
        <right url="teste_1_22/1/2/%v_%u.jpg"/>
        <back  url="teste_1_22/2/2/%v_%u.jpg"/>
        <left  url="teste_1_22/3/2/%v_%u.jpg"/>
        <up    url="teste_1_22/4/2/%v_%u.jpg"/>
        <down  url="teste_1_22/5/2/%v_%u.jpg"/>
      </level>
      <level tiledimagewidth="1232" tiledimageheight="1232">
        <front url="teste_1_22/0/1/%v_%u.jpg"/>
        <right url="teste_1_22/1/1/%v_%u.jpg"/>
        <back  url="teste_1_22/2/1/%v_%u.jpg"/>
        <left  url="teste_1_22/3/1/%v_%u.jpg"/>
        <up    url="teste_1_22/4/1/%v_%u.jpg"/>
        <down  url="teste_1_22/5/1/%v_%u.jpg"/>
      </level>
      <level tiledimagewidth="616" tiledimageheight="616">
        <front url="teste_1_22/0/0/%v_%u.jpg"/>
        <right url="teste_1_22/1/0/%v_%u.jpg"/>
        <back  url="teste_1_22/2/0/%v_%u.jpg"/>
        <left  url="teste_1_22/3/0/%v_%u.jpg"/>
        <up    url="teste_1_22/4/0/%v_%u.jpg"/>
        <down  url="teste_1_22/5/0/%v_%u.jpg"/>
      </level>
    </image>


  <action name="setzorder2onstandardspots">
    if (device.html5,
      ifnot (device.desktop,


      );
    );
  </action>  

</scene>



</krpano>